{
	"name": "000",
	"layers": [
		{
			"name": "Layer 0",
			"overriden": 0,
			"instances": [
				{
					"type": "MapEdge",
					"properties": {
						"left-margin": 16,
						"right-margin": 16,
						"top-margin": 16,
						"bottom-margin": 16,
						"edges": "stretch",
						"fill": "stretch",
						"initially-visible": true,
						"origin": "top-left",
						"seams": "overlap"
					},
					"uid": 22,
					"instanceVariables": {},
					"behaviors": {},
					"world": {
						"x": 0,
						"y": 0,
						"width": 1312,
						"height": 736,
						"originX": 0,
						"originY": 0,
						"color": [
							1,
							1,
							1,
							1
						],
						"angle": 0,
						"zElevation": 0
					}
				}
			],
			"sid": 296208619447693,
			"effectTypes": [],
			"isInitiallyVisible": true,
			"color": [
				1,
				1,
				1,
				1
			],
			"backgroundColor": [
				0.12156862745098039,
				0.1450980392156863,
				0.19215686274509805,
				1
			],
			"isTransparent": false,
			"parallaxX": 1,
			"parallaxY": 1,
			"scaleRate": 1,
			"forceOwnTexture": false,
			"useRenderCells": false,
			"blendMode": "normal",
			"global": false
		},
		{
			"name": "Level",
			"overriden": 0,
			"instances": [
				{
					"type": "TestSolid",
					"properties": {
						"initially-visible": true,
						"initial-animation": "Animation 1",
						"initial-frame": 0,
						"enable-collisions": true,
						"live-preview": false
					},
					"uid": 23,
					"instanceVariables": {},
					"behaviors": {
						"Solid": {
							"properties": {
								"enabled": true,
								"tags": ""
							}
						}
					},
					"world": {
						"x": -128,
						"y": -32,
						"width": 1568,
						"height": 256,
						"originX": 0,
						"originY": 0,
						"color": [
							1,
							1,
							1,
							1
						],
						"angle": 0,
						"zElevation": 0
					}
				}
			],
			"sid": 499724707006892,
			"effectTypes": [],
			"isInitiallyVisible": true,
			"color": [
				1,
				1,
				1,
				1
			],
			"backgroundColor": [
				0.12156862745098039,
				0.1450980392156863,
				0.19215686274509805,
				1
			],
			"isTransparent": true,
			"parallaxX": 1,
			"parallaxY": 1,
			"scaleRate": 1,
			"forceOwnTexture": false,
			"useRenderCells": false,
			"blendMode": "normal",
			"global": false
		},
		{
			"name": "Monsters",
			"overriden": 0,
			"instances": [],
			"sid": 395963684268162,
			"effectTypes": [],
			"isInitiallyVisible": true,
			"color": [
				1,
				1,
				1,
				1
			],
			"backgroundColor": [
				0.12156862745098039,
				0.1450980392156863,
				0.19215686274509805,
				1
			],
			"isTransparent": true,
			"parallaxX": 1,
			"parallaxY": 1,
			"scaleRate": 1,
			"forceOwnTexture": false,
			"useRenderCells": false,
			"blendMode": "normal",
			"global": false
		},
		{
			"name": "Netpeers",
			"overriden": 0,
			"instances": [],
			"sid": 925928414926797,
			"effectTypes": [],
			"isInitiallyVisible": true,
			"color": [
				1,
				1,
				1,
				1
			],
			"backgroundColor": [
				0.12156862745098039,
				0.1450980392156863,
				0.19215686274509805,
				1
			],
			"isTransparent": true,
			"parallaxX": 1,
			"parallaxY": 1,
			"scaleRate": 1,
			"forceOwnTexture": false,
			"useRenderCells": false,
			"blendMode": "normal",
			"global": false
		},
		{
			"name": "Assets_layer2",
			"overriden": 0,
			"instances": [],
			"sid": 712580066591416,
			"effectTypes": [],
			"isInitiallyVisible": true,
			"color": [
				1,
				1,
				1,
				1
			],
			"backgroundColor": [
				1,
				1,
				1,
				1
			],
			"isTransparent": true,
			"parallaxX": 1,
			"parallaxY": 1,
			"scaleRate": 1,
			"forceOwnTexture": false,
			"useRenderCells": false,
			"blendMode": "normal",
			"global": false
		},
		{
			"name": "UI",
			"overriden": 0,
			"instances": [
				{
					"type": "MapPlot",
					"properties": {
						"initially-visible": true,
						"initial-animation": "Default",
						"initial-frame": 0,
						"enable-collisions": true,
						"live-preview": false
					},
					"uid": 58,
					"instanceVariables": {
						"Destination": "001",
						"DestX": 48,
						"DestY": 496,
						"Active": true,
						"MinimapXShift": 1,
						"MinimapYShift": 0
					},
					"behaviors": {},
					"world": {
						"x": 1280,
						"y": 512,
						"width": 32,
						"height": 32,
						"originX": 0,
						"originY": 1,
						"color": [
							1,
							1,
							1,
							1
						],
						"angle": 0,
						"zElevation": 0
					}
				},
				{
					"type": "TestSolid",
					"properties": {
						"initially-visible": true,
						"initial-animation": "Animation 1",
						"initial-frame": 0,
						"enable-collisions": true,
						"live-preview": false
					},
					"uid": 35,
					"instanceVariables": {},
					"behaviors": {
						"Solid": {
							"properties": {
								"enabled": true,
								"tags": ""
							}
						}
					},
					"world": {
						"x": -128,
						"y": 224,
						"width": 320,
						"height": 736,
						"originX": 0,
						"originY": 0,
						"color": [
							1,
							1,
							1,
							1
						],
						"angle": 0,
						"zElevation": 0
					}
				},
				{
					"type": "TestSolid",
					"properties": {
						"initially-visible": true,
						"initial-animation": "Animation 1",
						"initial-frame": 0,
						"enable-collisions": true,
						"live-preview": false
					},
					"uid": 59,
					"instanceVariables": {},
					"behaviors": {
						"Solid": {
							"properties": {
								"enabled": true,
								"tags": ""
							}
						}
					},
					"world": {
						"x": 192,
						"y": 640,
						"width": 1120,
						"height": 320,
						"originX": 0,
						"originY": 0,
						"color": [
							1,
							1,
							1,
							1
						],
						"angle": 0,
						"zElevation": 0
					}
				}
			],
			"sid": 617524793948297,
			"effectTypes": [],
			"isInitiallyVisible": true,
			"color": [
				1,
				1,
				1,
				1
			],
			"backgroundColor": [
				0.12156862745098039,
				0.1450980392156863,
				0.19215686274509805,
				1
			],
			"isTransparent": true,
			"parallaxX": 1,
			"parallaxY": 1,
			"scaleRate": 1,
			"forceOwnTexture": false,
			"useRenderCells": false,
			"blendMode": "normal",
			"global": false
		},
		{
			"name": "FixedUI",
			"overriden": 1,
			"instances": [],
			"sid": 994143954535729,
			"effectTypes": [],
			"isInitiallyVisible": true,
			"color": [
				1,
				1,
				1,
				1
			],
			"backgroundColor": [
				0.12156862745098039,
				0.1450980392156863,
				0.19215686274509805,
				1
			],
			"isTransparent": true,
			"parallaxX": 0,
			"parallaxY": 0,
			"scaleRate": 1,
			"forceOwnTexture": false,
			"useRenderCells": false,
			"blendMode": "normal",
			"global": false
		},
		{
			"name": "_GAMEOBJECTS",
			"overriden": 0,
			"instances": [
				{
					"type": "Camera",
					"properties": {
						"initially-visible": false,
						"initial-animation": "Default",
						"initial-frame": 0,
						"enable-collisions": true,
						"live-preview": false
					},
					"uid": 36,
					"instanceVariables": {},
					"behaviors": {
						"ScrollTo": {
							"properties": {
								"enabled": true
							}
						}
					},
					"world": {
						"x": 416,
						"y": 320,
						"width": 32,
						"height": 32,
						"originX": 0.5,
						"originY": 0.5,
						"color": [
							1,
							1,
							1,
							1
						],
						"angle": 0,
						"zElevation": 0
					}
				}
			],
			"sid": 299137237000114,
			"effectTypes": [],
			"isInitiallyVisible": false,
			"color": [
				1,
				1,
				1,
				1
			],
			"backgroundColor": [
				0.12156862745098039,
				0.1450980392156863,
				0.19215686274509805,
				1
			],
			"isTransparent": true,
			"parallaxX": 1,
			"parallaxY": 1,
			"scaleRate": 1,
			"forceOwnTexture": false,
			"useRenderCells": false,
			"blendMode": "normal",
			"global": false
		},
		{
			"name": "Map",
			"overriden": 1,
			"instances": [],
			"sid": 699980336540901,
			"effectTypes": [],
			"isInitiallyVisible": true,
			"color": [
				1,
				1,
				1,
				1
			],
			"backgroundColor": [
				0.12156862745098039,
				0.1450980392156863,
				0.19215686274509805,
				1
			],
			"isTransparent": true,
			"parallaxX": 0,
			"parallaxY": 0,
			"scaleRate": 1,
			"forceOwnTexture": false,
			"useRenderCells": false,
			"blendMode": "normal",
			"global": false
		}
	],
	"sid": 878830360383095,
	"nonworld-instances": [],
	"effectTypes": [],
	"width": 1312,
	"height": 736,
	"unboundedScrolling": true,
	"eventSheet": "eMain"
}