{"propertiesBar":{"properties":[{"name":"Layout","expanded":true,"children":[{"name":"Size","expanded":false,"children":[]}]},{"name":"Effects","expanded":true,"children":[]},{"name":"Editor","expanded":true,"children":[{"name":"Margins","expanded":false,"children":[]},{"name":"Grid size","expanded":false,"children":[]},{"name":"Grid offset","expanded":false,"children":[]}]}],"scrollPosition":0},"grid":{"show":true,"snap":false,"width":32,"height":32,"offsetX":0,"offsetY":0},"marginWidth":1000,"marginHeight":1000,"showCollisionPolygons":false,"showMeshes":false,"showTranslucentInactiveLayers":false,"showSceneGraphConnections":true,"tabColor":[0.9000000000000001,0.9999999999999999,0.8000000000000002,1],"tabTextColor":null,"layers":[{"name":"FloorTexture","propertiesBar":{"properties":[{"name":"Layer properties","expanded":true,"children":[]},{"name":"Scroll & zoom","expanded":true,"children":[{"name":"Parallax","expanded":false,"children":[]}]},{"name":"Appearance","expanded":true,"children":[]},{"name":"Effects","expanded":true,"children":[]},{"name":"Editor","expanded":true,"children":[]}],"scrollPosition":0},"visibleInEditor":true,"locked":true,"parallaxInEditor":false,"opacity":1,"translucent":false},{"name":"BGParallax","propertiesBar":{"properties":[{"name":"Layer properties","expanded":true,"children":[]},{"name":"Scroll & zoom","expanded":true,"children":[{"name":"Parallax","expanded":false,"children":[]}]},{"name":"Appearance","expanded":true,"children":[]},{"name":"Effects","expanded":true,"children":[]},{"name":"Editor","expanded":true,"children":[]}],"scrollPosition":0},"visibleInEditor":true,"locked":true,"parallaxInEditor":false,"opacity":1,"translucent":false},{"name":"Level","propertiesBar":{"properties":[{"name":"Layer properties","expanded":true,"children":[]},{"name":"Scroll & zoom","expanded":true,"children":[{"name":"Parallax","expanded":false,"children":[]}]},{"name":"Appearance","expanded":true,"children":[]},{"name":"Effects","expanded":true,"children":[]},{"name":"Editor","expanded":true,"children":[]}],"scrollPosition":0},"visibleInEditor":true,"locked":true,"parallaxInEditor":false,"opacity":1,"translucent":false},{"name":"VOID","propertiesBar":{"properties":[{"name":"Layer properties","expanded":true,"children":[]},{"name":"Scroll & zoom","expanded":true,"children":[{"name":"Parallax","expanded":false,"children":[]}]},{"name":"Appearance","expanded":true,"children":[]},{"name":"Effects","expanded":true,"children":[]},{"name":"Editor","expanded":true,"children":[]}],"scrollPosition":0},"visibleInEditor":true,"locked":true,"parallaxInEditor":false,"opacity":1,"translucent":false},{"name":"Monsters","propertiesBar":{"properties":[{"name":"Layer properties","expanded":true,"children":[]},{"name":"Scroll & zoom","expanded":true,"children":[{"name":"Parallax","expanded":false,"children":[]}]},{"name":"Appearance","expanded":true,"children":[]},{"name":"Effects","expanded":true,"children":[]},{"name":"Editor","expanded":true,"children":[]}],"scrollPosition":0},"visibleInEditor":true,"locked":true,"parallaxInEditor":false,"opacity":1,"translucent":false},{"name":"Netpeers","propertiesBar":{"properties":[{"name":"Layer properties","expanded":true,"children":[]},{"name":"Scroll & zoom","expanded":true,"children":[{"name":"Parallax","expanded":false,"children":[]}]},{"name":"Appearance","expanded":true,"children":[]},{"name":"Effects","expanded":true,"children":[]},{"name":"Editor","expanded":true,"children":[]}],"scrollPosition":0},"visibleInEditor":true,"locked":true,"parallaxInEditor":false,"opacity":1,"translucent":false},{"name":"Edge","propertiesBar":{"properties":[{"name":"Layer properties","expanded":true,"children":[]},{"name":"Scroll & zoom","expanded":true,"children":[{"name":"Parallax","expanded":false,"children":[]}]},{"name":"Appearance","expanded":true,"children":[]},{"name":"Effects","expanded":true,"children":[]},{"name":"Editor","expanded":true,"children":[]}],"scrollPosition":0},"visibleInEditor":true,"locked":false,"parallaxInEditor":false,"opacity":1,"translucent":false},{"name":"Assets_underAll","propertiesBar":{"properties":[{"name":"Layer properties","expanded":true,"children":[]},{"name":"Scroll & zoom","expanded":true,"children":[{"name":"Parallax","expanded":false,"children":[]}]},{"name":"Appearance","expanded":true,"children":[]},{"name":"Effects","expanded":true,"children":[]},{"name":"Editor","expanded":true,"children":[]}],"scrollPosition":0},"visibleInEditor":true,"locked":false,"parallaxInEditor":false,"opacity":1,"translucent":false},{"name":"Assets_YasZ","propertiesBar":{"properties":[{"name":"Layer properties","expanded":true,"children":[]},{"name":"Scroll & zoom","expanded":true,"children":[{"name":"Parallax","expanded":false,"children":[]}]},{"name":"Appearance","expanded":true,"children":[]},{"name":"Effects","expanded":true,"children":[]},{"name":"Editor","expanded":true,"children":[]}],"scrollPosition":0},"visibleInEditor":true,"locked":false,"parallaxInEditor":false,"opacity":1,"translucent":false},{"name":"Assets_aboveAll","propertiesBar":{"properties":[{"name":"Layer properties","expanded":true,"children":[]},{"name":"Scroll & zoom","expanded":true,"children":[{"name":"Parallax","expanded":false,"children":[]}]},{"name":"Appearance","expanded":true,"children":[]},{"name":"Effects","expanded":true,"children":[]},{"name":"Editor","expanded":true,"children":[]}],"scrollPosition":0},"visibleInEditor":true,"locked":false,"parallaxInEditor":false,"opacity":1,"translucent":false},{"name":"VFX","propertiesBar":{"properties":[{"name":"Layer properties","expanded":true,"children":[]},{"name":"Scroll & zoom","expanded":true,"children":[{"name":"Parallax","expanded":false,"children":[]}]},{"name":"Appearance","expanded":true,"children":[]},{"name":"Effects","expanded":true,"children":[]},{"name":"Editor","expanded":true,"children":[]}],"scrollPosition":0},"visibleInEditor":false,"locked":true,"parallaxInEditor":false,"opacity":1,"translucent":false},{"name":"Cadran","propertiesBar":{"properties":[{"name":"Layer properties","expanded":true,"children":[]},{"name":"Scroll & zoom","expanded":true,"children":[{"name":"Parallax","expanded":false,"children":[]}]},{"name":"Appearance","expanded":true,"children":[]},{"name":"Effects","expanded":true,"children":[]},{"name":"Editor","expanded":true,"children":[]}],"scrollPosition":0},"visibleInEditor":true,"locked":true,"parallaxInEditor":false,"opacity":1,"translucent":false},{"name":"UI","propertiesBar":{"properties":[{"name":"Layer properties","expanded":true,"children":[]},{"name":"Scroll & zoom","expanded":true,"children":[{"name":"Parallax","expanded":false,"children":[]}]},{"name":"Appearance","expanded":true,"children":[]},{"name":"Effects","expanded":true,"children":[]},{"name":"Editor","expanded":true,"children":[]}],"scrollPosition":0},"visibleInEditor":true,"locked":true,"parallaxInEditor":false,"opacity":1,"translucent":false},{"name":"IGM_Dialogs","propertiesBar":{},"visibleInEditor":false,"locked":true,"parallaxInEditor":false,"opacity":1,"translucent":false},{"name":"IGM_Inventory","propertiesBar":{},"visibleInEditor":false,"locked":true,"parallaxInEditor":false,"opacity":1,"translucent":false},{"name":"IGM_Skills","propertiesBar":{},"visibleInEditor":false,"locked":true,"parallaxInEditor":false,"opacity":1,"translucent":false},{"name":"IGM_DNA","propertiesBar":{},"visibleInEditor":false,"locked":true,"parallaxInEditor":false,"opacity":1,"translucent":false},{"name":"IGM_Journal","propertiesBar":{},"visibleInEditor":false,"locked":true,"parallaxInEditor":false,"opacity":1,"translucent":false},{"name":"FixedUI","propertiesBar":{"properties":[{"name":"Layer properties","expanded":true,"children":[]},{"name":"Scroll & zoom","expanded":true,"children":[{"name":"Parallax","expanded":false,"children":[]}]},{"name":"Appearance","expanded":true,"children":[]},{"name":"Effects","expanded":true,"children":[]},{"name":"Editor","expanded":true,"children":[]}],"scrollPosition":0},"visibleInEditor":true,"locked":true,"parallaxInEditor":false,"opacity":1,"translucent":false},{"name":"Map","propertiesBar":{"properties":[{"name":"Layer properties","expanded":true,"children":[]},{"name":"Scroll & zoom","expanded":true,"children":[{"name":"Parallax","expanded":false,"children":[]}]},{"name":"Appearance","expanded":true,"children":[]},{"name":"Effects","expanded":true,"children":[]},{"name":"Editor","expanded":true,"children":[]}],"scrollPosition":0},"visibleInEditor":true,"locked":true,"parallaxInEditor":false,"opacity":1,"translucent":false},{"name":"_GAMEOBJECTS","propertiesBar":{"properties":[{"name":"Layer properties","expanded":true,"children":[]},{"name":"Scroll & zoom","expanded":true,"children":[{"name":"Parallax","expanded":false,"children":[]}]},{"name":"Appearance","expanded":true,"children":[]},{"name":"Effects","expanded":true,"children":[]},{"name":"Editor","expanded":true,"children":[]}],"scrollPosition":0},"visibleInEditor":false,"locked":false,"parallaxInEditor":false,"opacity":1,"translucent":false},{"name":"GridGraph","propertiesBar":{"properties":[{"name":"Layer properties","expanded":true,"children":[]},{"name":"Scroll & zoom","expanded":true,"children":[{"name":"Parallax","expanded":false,"children":[]}]},{"name":"Appearance","expanded":true,"children":[]},{"name":"Effects","expanded":true,"children":[]},{"name":"Editor","expanded":true,"children":[]}],"scrollPosition":0},"visibleInEditor":true,"locked":true,"parallaxInEditor":false,"opacity":1,"translucent":false},{"name":"_DEBUGGING","propertiesBar":{"properties":[{"name":"Layer properties","expanded":true,"children":[]},{"name":"Scroll & zoom","expanded":true,"children":[{"name":"Parallax","expanded":false,"children":[]}]},{"name":"Appearance","expanded":true,"children":[]},{"name":"Effects","expanded":true,"children":[]},{"name":"Editor","expanded":true,"children":[]}],"scrollPosition":0},"visibleInEditor":true,"locked":true,"parallaxInEditor":false,"opacity":1,"translucent":false},{"name":"MUSIC","propertiesBar":{"properties":[{"name":"Layer properties","expanded":true,"children":[]},{"name":"Scroll & zoom","expanded":true,"children":[{"name":"Parallax","expanded":false,"children":[]}]},{"name":"Appearance","expanded":true,"children":[]},{"name":"Effects","expanded":true,"children":[]},{"name":"Editor","expanded":true,"children":[]}],"scrollPosition":0},"visibleInEditor":true,"locked":false,"parallaxInEditor":false,"opacity":1,"translucent":false}],"view":{"x":503.8636363636383,"y":510.9545454545473,"z":118.18181818181833,"activeLayer":"MUSIC"},"selectedInstances":[],"instanceCollections":[{"uids":[22,25,28,32,58,409,412,421,423,434,435],"properties":{"properties":[{"name":"Common","expanded":true,"children":[{"name":"Position","expanded":false,"children":[]},{"name":"Size","expanded":false,"children":[]}]},{"name":"Effects","expanded":true,"children":[]}],"scrollPosition":0}},{"uids":[22,25,28,32,58,412,421,423,434,435],"properties":{"properties":[{"name":"Common","expanded":true,"children":[{"name":"Position","expanded":false,"children":[]},{"name":"Size","expanded":false,"children":[]}]},{"name":"Effects","expanded":true,"children":[]}],"scrollPosition":0}},{"uids":[10,19,22,23,25,28,29,32,35,36,44,45,46,47,58,59,409,412,421,423,434,435],"properties":{"properties":[{"name":"Common","expanded":true,"children":[{"name":"Position","expanded":false,"children":[]},{"name":"Size","expanded":false,"children":[]}]},{"name":"Effects","expanded":true,"children":[]}],"scrollPosition":0}},{"uids":[22,23,25,28,32,35,36,58,59,409,412,421,434,435],"properties":{"properties":[{"name":"Common","expanded":true,"children":[{"name":"Position","expanded":false,"children":[]},{"name":"Size","expanded":false,"children":[]}]},{"name":"Effects","expanded":true,"children":[]}],"scrollPosition":0}},{"uids":[455,456,457,458,459,460,461,462,463,464,465,466,467,468,469],"properties":{"properties":[{"name":"Object type properties","expanded":true,"children":[]},{"name":"Common","expanded":true,"children":[{"name":"Position","expanded":false,"children":[]},{"name":"Size","expanded":false,"children":[]}]},{"name":"Instance variables","expanded":true,"children":[]},{"name":"Behaviors","expanded":true,"children":[]},{"name":"Effects","expanded":true,"children":[]},{"name":"Container","expanded":true,"children":[]},{"name":"Properties","expanded":true,"children":[]}],"scrollPosition":0}},{"uids":[23,35],"properties":{"properties":[{"name":"Object type properties","expanded":true,"children":[]},{"name":"Common","expanded":true,"children":[{"name":"Position","expanded":false,"children":[]},{"name":"Size","expanded":false,"children":[]}]},{"name":"Instance variables","expanded":true,"children":[]},{"name":"Behaviors","expanded":true,"children":[{"name":"Solid [Solid]","expanded":true,"children":[]}]},{"name":"Effects","expanded":true,"children":[]},{"name":"Container","expanded":true,"children":[]},{"name":"Properties","expanded":true,"children":[]}],"scrollPosition":0}},{"uids":[412,434],"properties":{"properties":[{"name":"Object type properties","expanded":true,"children":[]},{"name":"Common","expanded":true,"children":[{"name":"Position","expanded":false,"children":[]},{"name":"Size","expanded":false,"children":[]}]},{"name":"Instance variables","expanded":true,"children":[]},{"name":"Behaviors","expanded":true,"children":[]},{"name":"Effects","expanded":true,"children":[{"name":"Water","expanded":true,"children":[]}]},{"name":"Container","expanded":true,"children":[]},{"name":"Properties","expanded":true,"children":[]}],"scrollPosition":0}},{"uids":[22,58],"properties":{"properties":[{"name":"Common","expanded":true,"children":[{"name":"Position","expanded":false,"children":[]},{"name":"Size","expanded":false,"children":[]}]},{"name":"Effects","expanded":true,"children":[]}],"scrollPosition":0}},{"uids":[524,525],"properties":{"properties":[{"name":"Object type properties","expanded":true,"children":[]},{"name":"Common","expanded":true,"children":[{"name":"Position","expanded":false,"children":[]},{"name":"Size","expanded":false,"children":[]}]},{"name":"Instance variables","expanded":true,"children":[]},{"name":"Behaviors","expanded":true,"children":[]},{"name":"Effects","expanded":true,"children":[]},{"name":"Container","expanded":true,"children":[]},{"name":"Properties","expanded":true,"children":[]}],"scrollPosition":0}},{"uids":[412,564],"properties":{"properties":[{"name":"Common","expanded":true,"children":[{"name":"Position","expanded":false,"children":[]},{"name":"Size","expanded":false,"children":[]}]},{"name":"Effects","expanded":true,"children":[]}],"scrollPosition":0}},{"uids":[544,693],"properties":{"properties":[{"name":"Object type properties","expanded":true,"children":[]},{"name":"Common","expanded":true,"children":[{"name":"Position","expanded":false,"children":[]},{"name":"Size","expanded":false,"children":[]}]},{"name":"Instance variables","expanded":true,"children":[]},{"name":"Behaviors","expanded":true,"children":[]},{"name":"Effects","expanded":true,"children":[]},{"name":"Container","expanded":true,"children":[]},{"name":"Properties","expanded":true,"children":[]}],"scrollPosition":0}},{"uids":[23,35,59],"properties":{"properties":[{"name":"Object type properties","expanded":true,"children":[]},{"name":"Common","expanded":true,"children":[{"name":"Position","expanded":false,"children":[]},{"name":"Size","expanded":false,"children":[]}]},{"name":"Instance variables","expanded":true,"children":[]},{"name":"Behaviors","expanded":true,"children":[{"name":"Solid [Solid]","expanded":true,"children":[]}]},{"name":"Effects","expanded":true,"children":[]},{"name":"Container","expanded":true,"children":[]},{"name":"Properties","expanded":true,"children":[]}],"scrollPosition":0}},{"uids":[412,421,434],"properties":{"properties":[{"name":"Common","expanded":true,"children":[{"name":"Position","expanded":false,"children":[]},{"name":"Size","expanded":false,"children":[]}]},{"name":"Effects","expanded":true,"children":[]}],"scrollPosition":0}},{"uids":[22,412,434],"properties":{"properties":[{"name":"Common","expanded":true,"children":[{"name":"Position","expanded":false,"children":[]},{"name":"Size","expanded":false,"children":[]}]},{"name":"Effects","expanded":true,"children":[]}],"scrollPosition":0}},{"uids":[452,453,454],"properties":{"properties":[{"name":"Object type properties","expanded":true,"children":[]},{"name":"Common","expanded":true,"children":[{"name":"Position","expanded":false,"children":[]},{"name":"Size","expanded":false,"children":[]}]},{"name":"Effects","expanded":true,"children":[]},{"name":"Properties","expanded":true,"children":[]}],"scrollPosition":0}},{"uids":[452,453,454],"properties":{"properties":[{"name":"Object type properties","expanded":true,"children":[]},{"name":"Common","expanded":true,"children":[{"name":"Position","expanded":false,"children":[]},{"name":"Size","expanded":false,"children":[]}]},{"name":"Effects","expanded":true,"children":[]},{"name":"Properties","expanded":true,"children":[]}],"scrollPosition":0}},{"uids":[412,434,435],"properties":{"properties":[{"name":"Object type properties","expanded":true,"children":[]},{"name":"Common","expanded":true,"children":[{"name":"Position","expanded":false,"children":[]},{"name":"Size","expanded":false,"children":[]}]},{"name":"Instance variables","expanded":true,"children":[]},{"name":"Behaviors","expanded":true,"children":[]},{"name":"Effects","expanded":true,"children":[{"name":"Water","expanded":true,"children":[]}]},{"name":"Container","expanded":true,"children":[]},{"name":"Properties","expanded":true,"children":[]}],"scrollPosition":0}},{"uids":[523,524,525],"properties":{"properties":[{"name":"Object type properties","expanded":true,"children":[]},{"name":"Common","expanded":true,"children":[{"name":"Position","expanded":false,"children":[]},{"name":"Size","expanded":false,"children":[]}]},{"name":"Instance variables","expanded":true,"children":[]},{"name":"Behaviors","expanded":true,"children":[]},{"name":"Effects","expanded":true,"children":[]},{"name":"Container","expanded":true,"children":[]},{"name":"Properties","expanded":true,"children":[]}],"scrollPosition":0}},{"uids":[544,693,694],"properties":{"properties":[{"name":"Object type properties","expanded":true,"children":[]},{"name":"Common","expanded":true,"children":[{"name":"Position","expanded":false,"children":[]},{"name":"Size","expanded":false,"children":[]}]},{"name":"Instance variables","expanded":true,"children":[]},{"name":"Behaviors","expanded":true,"children":[]},{"name":"Effects","expanded":true,"children":[]},{"name":"Container","expanded":true,"children":[]},{"name":"Properties","expanded":true,"children":[]}],"scrollPosition":0}},{"uids":[22,412,421,434],"properties":{"properties":[{"name":"Common","expanded":true,"children":[{"name":"Position","expanded":false,"children":[]},{"name":"Size","expanded":false,"children":[]}]},{"name":"Effects","expanded":true,"children":[]}],"scrollPosition":0}},{"uids":[544,693,694,695],"properties":{"properties":[{"name":"Family properties","expanded":true,"children":[]},{"name":"Common","expanded":true,"children":[{"name":"Position","expanded":false,"children":[]},{"name":"Size","expanded":false,"children":[]}]},{"name":"Family instance variables","expanded":true,"children":[]},{"name":"Family behaviors","expanded":true,"children":[]},{"name":"Family effects","expanded":true,"children":[]},{"name":"Properties","expanded":true,"children":[]}],"scrollPosition":0}},{"uids":[453,690],"properties":{"properties":[{"name":"Object type properties","expanded":true,"children":[]},{"name":"Common","expanded":true,"children":[{"name":"Position","expanded":false,"children":[]},{"name":"Size","expanded":false,"children":[]}]},{"name":"Instance variables","expanded":true,"children":[]},{"name":"Behaviors","expanded":true,"children":[{"name":"Sine","expanded":true,"children":[]},{"name":"Sine2","expanded":true,"children":[]}]},{"name":"Effects","expanded":true,"children":[]},{"name":"Container","expanded":true,"children":[]},{"name":"Properties","expanded":true,"children":[]}],"scrollPosition":0}},{"uids":[453,615,690],"properties":{"properties":[{"name":"Object type properties","expanded":true,"children":[]},{"name":"Common","expanded":true,"children":[{"name":"Position","expanded":false,"children":[]},{"name":"Size","expanded":false,"children":[]}]},{"name":"Effects","expanded":true,"children":[]},{"name":"Properties","expanded":true,"children":[]}],"scrollPosition":0}},{"uids":[454],"properties":{"properties":[{"name":"Object type properties","expanded":true,"children":[]},{"name":"Common","expanded":true,"children":[{"name":"Position","expanded":false,"children":[]},{"name":"Size","expanded":false,"children":[]}]},{"name":"Instance variables","expanded":true,"children":[]},{"name":"Behaviors","expanded":true,"children":[{"name":"DialogsActivationRange","expanded":true,"children":[]}]},{"name":"Effects","expanded":true,"children":[]},{"name":"Container","expanded":true,"children":[]},{"name":"Properties","expanded":true,"children":[]}],"scrollPosition":0}},{"uids":[35],"properties":{"properties":[{"name":"Object type properties","expanded":true,"children":[]},{"name":"Common","expanded":true,"children":[{"name":"Position","expanded":false,"children":[]},{"name":"Size","expanded":false,"children":[]}]},{"name":"Instance variables","expanded":true,"children":[]},{"name":"Behaviors","expanded":true,"children":[{"name":"Solid [Solid]","expanded":true,"children":[]}]},{"name":"Effects","expanded":true,"children":[]},{"name":"Container","expanded":true,"children":[]},{"name":"Properties","expanded":true,"children":[]}],"scrollPosition":0}},{"uids":[35],"properties":{"properties":[{"name":"Object type properties","expanded":true,"children":[]},{"name":"Common","expanded":true,"children":[{"name":"Position","expanded":false,"children":[]},{"name":"Size","expanded":false,"children":[]}]},{"name":"Instance variables","expanded":true,"children":[]},{"name":"Behaviors","expanded":true,"children":[{"name":"Solid [Solid]","expanded":true,"children":[]}]},{"name":"Effects","expanded":true,"children":[]},{"name":"Container","expanded":true,"children":[]},{"name":"Properties","expanded":true,"children":[]}],"scrollPosition":0}},{"uids":[36],"properties":{"properties":[{"name":"Object type properties","expanded":true,"children":[]},{"name":"Common","expanded":true,"children":[{"name":"Position","expanded":false,"children":[]},{"name":"Size","expanded":false,"children":[]}]},{"name":"Instance variables","expanded":true,"children":[]},{"name":"Behaviors","expanded":true,"children":[{"name":"ScrollTo","expanded":true,"children":[]}]},{"name":"Effects","expanded":true,"children":[]},{"name":"Container","expanded":true,"children":[]},{"name":"Properties","expanded":true,"children":[]}],"scrollPosition":0}},{"uids":[453],"properties":{"properties":[{"name":"Object type properties","expanded":true,"children":[]},{"name":"Common","expanded":true,"children":[{"name":"Position","expanded":false,"children":[]},{"name":"Size","expanded":false,"children":[]}]},{"name":"Instance variables","expanded":true,"children":[]},{"name":"Behaviors","expanded":true,"children":[{"name":"Sine","expanded":true,"children":[]},{"name":"Sine2","expanded":true,"children":[]}]},{"name":"Effects","expanded":true,"children":[]},{"name":"Container","expanded":true,"children":[]},{"name":"Properties","expanded":true,"children":[]}],"scrollPosition":0}},{"uids":[455],"properties":{"properties":[{"name":"Object type properties","expanded":true,"children":[]},{"name":"Common","expanded":true,"children":[{"name":"Position","expanded":false,"children":[]},{"name":"Size","expanded":false,"children":[]}]},{"name":"Instance variables","expanded":true,"children":[]},{"name":"Behaviors","expanded":true,"children":[]},{"name":"Effects","expanded":true,"children":[]},{"name":"Container","expanded":true,"children":[]},{"name":"Properties","expanded":true,"children":[]}],"scrollPosition":0}},{"uids":[460],"properties":{"properties":[{"name":"Object type properties","expanded":true,"children":[]},{"name":"Common","expanded":true,"children":[{"name":"Position","expanded":false,"children":[]},{"name":"Size","expanded":false,"children":[]}]},{"name":"Instance variables","expanded":true,"children":[]},{"name":"Behaviors","expanded":true,"children":[]},{"name":"Effects","expanded":true,"children":[]},{"name":"Container","expanded":true,"children":[]},{"name":"Properties","expanded":true,"children":[]}],"scrollPosition":0}},{"uids":[461],"properties":{"properties":[{"name":"Object type properties","expanded":true,"children":[]},{"name":"Common","expanded":true,"children":[{"name":"Position","expanded":false,"children":[]},{"name":"Size","expanded":false,"children":[]}]},{"name":"Instance variables","expanded":true,"children":[]},{"name":"Behaviors","expanded":true,"children":[]},{"name":"Effects","expanded":true,"children":[]},{"name":"Container","expanded":true,"children":[]},{"name":"Properties","expanded":true,"children":[]}],"scrollPosition":0}},{"uids":[463],"properties":{"properties":[{"name":"Object type properties","expanded":true,"children":[]},{"name":"Common","expanded":true,"children":[{"name":"Position","expanded":false,"children":[]},{"name":"Size","expanded":false,"children":[]}]},{"name":"Instance variables","expanded":true,"children":[]},{"name":"Behaviors","expanded":true,"children":[]},{"name":"Effects","expanded":true,"children":[]},{"name":"Container","expanded":true,"children":[]},{"name":"Properties","expanded":true,"children":[]}],"scrollPosition":0}},{"uids":[457],"properties":{"properties":[{"name":"Object type properties","expanded":true,"children":[]},{"name":"Common","expanded":true,"children":[{"name":"Position","expanded":false,"children":[]},{"name":"Size","expanded":false,"children":[]}]},{"name":"Instance variables","expanded":true,"children":[]},{"name":"Behaviors","expanded":true,"children":[]},{"name":"Effects","expanded":true,"children":[]},{"name":"Container","expanded":true,"children":[]},{"name":"Properties","expanded":true,"children":[]}],"scrollPosition":0}},{"uids":[456],"properties":{"properties":[{"name":"Object type properties","expanded":true,"children":[]},{"name":"Common","expanded":true,"children":[{"name":"Position","expanded":false,"children":[]},{"name":"Size","expanded":false,"children":[]}]},{"name":"Instance variables","expanded":true,"children":[]},{"name":"Behaviors","expanded":true,"children":[]},{"name":"Effects","expanded":true,"children":[]},{"name":"Container","expanded":true,"children":[]},{"name":"Properties","expanded":true,"children":[]}],"scrollPosition":0}},{"uids":[465],"properties":{"properties":[{"name":"Object type properties","expanded":true,"children":[]},{"name":"Common","expanded":true,"children":[{"name":"Position","expanded":false,"children":[]},{"name":"Size","expanded":false,"children":[]}]},{"name":"Instance variables","expanded":true,"children":[]},{"name":"Behaviors","expanded":true,"children":[]},{"name":"Effects","expanded":true,"children":[]},{"name":"Container","expanded":true,"children":[]},{"name":"Properties","expanded":true,"children":[]}],"scrollPosition":0}},{"uids":[464],"properties":{"properties":[{"name":"Object type properties","expanded":true,"children":[]},{"name":"Common","expanded":true,"children":[{"name":"Position","expanded":false,"children":[]},{"name":"Size","expanded":false,"children":[]}]},{"name":"Instance variables","expanded":true,"children":[]},{"name":"Behaviors","expanded":true,"children":[]},{"name":"Effects","expanded":true,"children":[]},{"name":"Container","expanded":true,"children":[]},{"name":"Properties","expanded":true,"children":[]}],"scrollPosition":0}},{"uids":[459],"properties":{"properties":[{"name":"Object type properties","expanded":true,"children":[]},{"name":"Common","expanded":true,"children":[{"name":"Position","expanded":false,"children":[]},{"name":"Size","expanded":false,"children":[]}]},{"name":"Instance variables","expanded":true,"children":[]},{"name":"Behaviors","expanded":true,"children":[]},{"name":"Effects","expanded":true,"children":[]},{"name":"Container","expanded":true,"children":[]},{"name":"Properties","expanded":true,"children":[]}],"scrollPosition":0}},{"uids":[467],"properties":{"properties":[{"name":"Object type properties","expanded":true,"children":[]},{"name":"Common","expanded":true,"children":[{"name":"Position","expanded":false,"children":[]},{"name":"Size","expanded":false,"children":[]}]},{"name":"Instance variables","expanded":true,"children":[]},{"name":"Behaviors","expanded":true,"children":[]},{"name":"Effects","expanded":true,"children":[]},{"name":"Container","expanded":true,"children":[]},{"name":"Properties","expanded":true,"children":[]}],"scrollPosition":0}},{"uids":[468],"properties":{"properties":[{"name":"Object type properties","expanded":true,"children":[]},{"name":"Common","expanded":true,"children":[{"name":"Position","expanded":false,"children":[]},{"name":"Size","expanded":false,"children":[]}]},{"name":"Instance variables","expanded":true,"children":[]},{"name":"Behaviors","expanded":true,"children":[]},{"name":"Effects","expanded":true,"children":[]},{"name":"Container","expanded":true,"children":[]},{"name":"Properties","expanded":true,"children":[]}],"scrollPosition":0}},{"uids":[469],"properties":{"properties":[{"name":"Object type properties","expanded":true,"children":[]},{"name":"Common","expanded":true,"children":[{"name":"Position","expanded":false,"children":[]},{"name":"Size","expanded":false,"children":[]}]},{"name":"Instance variables","expanded":true,"children":[]},{"name":"Behaviors","expanded":true,"children":[]},{"name":"Effects","expanded":true,"children":[]},{"name":"Container","expanded":true,"children":[]},{"name":"Properties","expanded":true,"children":[]}],"scrollPosition":0}},{"uids":[523],"properties":{"properties":[{"name":"Object type properties","expanded":true,"children":[]},{"name":"Common","expanded":true,"children":[{"name":"Position","expanded":false,"children":[]},{"name":"Size","expanded":false,"children":[]}]},{"name":"Instance variables","expanded":true,"children":[]},{"name":"Behaviors","expanded":true,"children":[]},{"name":"Effects","expanded":true,"children":[]},{"name":"Container","expanded":true,"children":[]},{"name":"Properties","expanded":true,"children":[]}],"scrollPosition":0}},{"uids":[524],"properties":{"properties":[{"name":"Object type properties","expanded":true,"children":[]},{"name":"Common","expanded":true,"children":[{"name":"Position","expanded":false,"children":[]},{"name":"Size","expanded":false,"children":[]}]},{"name":"Instance variables","expanded":true,"children":[]},{"name":"Behaviors","expanded":true,"children":[]},{"name":"Effects","expanded":true,"children":[]},{"name":"Container","expanded":true,"children":[]},{"name":"Properties","expanded":true,"children":[]}],"scrollPosition":0}},{"uids":[458],"properties":{"properties":[{"name":"Object type properties","expanded":true,"children":[]},{"name":"Common","expanded":true,"children":[{"name":"Position","expanded":false,"children":[]},{"name":"Size","expanded":false,"children":[]}]},{"name":"Instance variables","expanded":true,"children":[]},{"name":"Behaviors","expanded":true,"children":[]},{"name":"Effects","expanded":true,"children":[]},{"name":"Container","expanded":true,"children":[]},{"name":"Properties","expanded":true,"children":[]}],"scrollPosition":0}},{"uids":[23],"properties":{"properties":[{"name":"Object type properties","expanded":true,"children":[]},{"name":"Common","expanded":true,"children":[{"name":"Position","expanded":false,"children":[]},{"name":"Size","expanded":false,"children":[]}]},{"name":"Instance variables","expanded":true,"children":[]},{"name":"Behaviors","expanded":true,"children":[{"name":"Solid [Solid]","expanded":true,"children":[]}]},{"name":"Effects","expanded":true,"children":[]},{"name":"Container","expanded":true,"children":[]},{"name":"Properties","expanded":true,"children":[]}],"scrollPosition":0}},{"uids":[466],"properties":{"properties":[{"name":"Object type properties","expanded":true,"children":[]},{"name":"Common","expanded":true,"children":[{"name":"Position","expanded":false,"children":[]},{"name":"Size","expanded":false,"children":[]}]},{"name":"Instance variables","expanded":true,"children":[]},{"name":"Behaviors","expanded":true,"children":[]},{"name":"Effects","expanded":true,"children":[]},{"name":"Container","expanded":true,"children":[]},{"name":"Properties","expanded":true,"children":[]}],"scrollPosition":0}},{"uids":[545],"properties":{"properties":[{"name":"Object type properties","expanded":true,"children":[]},{"name":"Common","expanded":true,"children":[{"name":"Position","expanded":false,"children":[]},{"name":"Size","expanded":false,"children":[]}]},{"name":"Instance variables","expanded":true,"children":[]},{"name":"Behaviors","expanded":true,"children":[]},{"name":"Effects","expanded":true,"children":[]},{"name":"Container","expanded":true,"children":[]},{"name":"Properties","expanded":true,"children":[]}],"scrollPosition":0}},{"uids":[530],"properties":{"properties":[{"name":"Object type properties","expanded":true,"children":[]},{"name":"Common","expanded":true,"children":[{"name":"Position","expanded":false,"children":[]},{"name":"Size","expanded":false,"children":[]}]},{"name":"Instance variables","expanded":true,"children":[]},{"name":"Behaviors","expanded":true,"children":[]},{"name":"Effects","expanded":true,"children":[]},{"name":"Container","expanded":true,"children":[]},{"name":"Properties","expanded":true,"children":[]},{"name":"Initial particle properties","expanded":true,"children":[]},{"name":"Particle lifetime properties","expanded":true,"children":[]}],"scrollPosition":0}},{"uids":[525],"properties":{"properties":[{"name":"Object type properties","expanded":true,"children":[]},{"name":"Common","expanded":true,"children":[{"name":"Position","expanded":false,"children":[]},{"name":"Size","expanded":false,"children":[]}]},{"name":"Instance variables","expanded":true,"children":[]},{"name":"Behaviors","expanded":true,"children":[]},{"name":"Effects","expanded":true,"children":[]},{"name":"Container","expanded":true,"children":[]},{"name":"Properties","expanded":true,"children":[]}],"scrollPosition":0}},{"uids":[412],"properties":{"properties":[{"name":"Object type properties","expanded":true,"children":[]},{"name":"Common","expanded":true,"children":[{"name":"Position","expanded":false,"children":[]},{"name":"Size","expanded":false,"children":[]}]},{"name":"Instance variables","expanded":true,"children":[]},{"name":"Behaviors","expanded":true,"children":[]},{"name":"Effects","expanded":true,"children":[{"name":"Water","expanded":true,"children":[]}]},{"name":"Container","expanded":true,"children":[]},{"name":"Properties","expanded":true,"children":[]}],"scrollPosition":0}},{"uids":[58],"properties":{"properties":[{"name":"Object type properties","expanded":true,"children":[]},{"name":"Common","expanded":true,"children":[{"name":"Position","expanded":false,"children":[]},{"name":"Size","expanded":false,"children":[]}]},{"name":"Instance variables","expanded":true,"children":[]},{"name":"Behaviors","expanded":true,"children":[]},{"name":"Effects","expanded":true,"children":[]},{"name":"Container","expanded":true,"children":[]},{"name":"Properties","expanded":true,"children":[]}],"scrollPosition":0}},{"uids":[434],"properties":{"properties":[{"name":"Object type properties","expanded":true,"children":[]},{"name":"Common","expanded":true,"children":[{"name":"Position","expanded":false,"children":[]},{"name":"Size","expanded":false,"children":[]}]},{"name":"Instance variables","expanded":true,"children":[]},{"name":"Behaviors","expanded":true,"children":[]},{"name":"Effects","expanded":true,"children":[{"name":"Water","expanded":true,"children":[]}]},{"name":"Container","expanded":true,"children":[]},{"name":"Properties","expanded":true,"children":[]}],"scrollPosition":0}},{"uids":[423],"properties":{"properties":[{"name":"Object type properties","expanded":true,"children":[]},{"name":"Common","expanded":true,"children":[{"name":"Position","expanded":false,"children":[]},{"name":"Size","expanded":false,"children":[]}]},{"name":"Instance variables","expanded":true,"children":[]},{"name":"Behaviors","expanded":true,"children":[]},{"name":"Effects","expanded":true,"children":[{"name":"Water","expanded":true,"children":[]}]},{"name":"Container","expanded":true,"children":[]},{"name":"Properties","expanded":true,"children":[]}],"scrollPosition":0}},{"uids":[423],"properties":{"properties":[{"name":"Object type properties","expanded":true,"children":[]},{"name":"Common","expanded":true,"children":[{"name":"Position","expanded":false,"children":[]},{"name":"Size","expanded":false,"children":[]}]},{"name":"Instance variables","expanded":true,"children":[]},{"name":"Behaviors","expanded":true,"children":[]},{"name":"Effects","expanded":true,"children":[{"name":"Water","expanded":true,"children":[]}]},{"name":"Container","expanded":true,"children":[]},{"name":"Properties","expanded":true,"children":[]}],"scrollPosition":0}},{"uids":[59],"properties":{"properties":[{"name":"Object type properties","expanded":true,"children":[]},{"name":"Common","expanded":true,"children":[{"name":"Position","expanded":false,"children":[]},{"name":"Size","expanded":false,"children":[]}]},{"name":"Instance variables","expanded":true,"children":[]},{"name":"Behaviors","expanded":true,"children":[{"name":"Solid [Solid]","expanded":true,"children":[]}]},{"name":"Effects","expanded":true,"children":[]},{"name":"Container","expanded":true,"children":[]},{"name":"Properties","expanded":true,"children":[]}],"scrollPosition":0}},{"uids":[407],"properties":{"properties":[{"name":"Object type properties","expanded":true,"children":[]},{"name":"Common","expanded":true,"children":[{"name":"Position","expanded":false,"children":[]},{"name":"Size","expanded":false,"children":[]}]},{"name":"Instance variables","expanded":true,"children":[]},{"name":"Behaviors","expanded":true,"children":[{"name":"Solid [Solid]","expanded":true,"children":[]}]},{"name":"Effects","expanded":true,"children":[]},{"name":"Container","expanded":true,"children":[]},{"name":"Properties","expanded":true,"children":[]}],"scrollPosition":0}},{"uids":[638],"properties":{"properties":[{"name":"Object type properties","expanded":true,"children":[]},{"name":"Common","expanded":true,"children":[{"name":"Position","expanded":false,"children":[]},{"name":"Size","expanded":false,"children":[]}]},{"name":"Instance variables","expanded":true,"children":[]},{"name":"Behaviors","expanded":true,"children":[{"name":"Solid [Solid]","expanded":true,"children":[]}]},{"name":"Effects","expanded":true,"children":[]},{"name":"Container","expanded":true,"children":[]},{"name":"Properties","expanded":true,"children":[]}],"scrollPosition":0}},{"uids":[547],"properties":{"properties":[{"name":"Object type properties","expanded":true,"children":[]},{"name":"Common","expanded":true,"children":[{"name":"Position","expanded":false,"children":[]},{"name":"Size","expanded":false,"children":[]}]},{"name":"Instance variables","expanded":true,"children":[]},{"name":"Behaviors","expanded":true,"children":[{"name":"Solid [Solid]","expanded":true,"children":[]}]},{"name":"Effects","expanded":true,"children":[]},{"name":"Container","expanded":true,"children":[]},{"name":"Properties","expanded":true,"children":[]}],"scrollPosition":0}},{"uids":[546],"properties":{"properties":[{"name":"Object type properties","expanded":true,"children":[]},{"name":"Common","expanded":true,"children":[{"name":"Position","expanded":false,"children":[]},{"name":"Size","expanded":false,"children":[]}]},{"name":"Instance variables","expanded":true,"children":[]},{"name":"Behaviors","expanded":true,"children":[{"name":"Solid [Solid]","expanded":true,"children":[]}]},{"name":"Effects","expanded":true,"children":[]},{"name":"Container","expanded":true,"children":[]},{"name":"Properties","expanded":true,"children":[]}],"scrollPosition":0}},{"uids":[546],"properties":{"properties":[{"name":"Object type properties","expanded":true,"children":[]},{"name":"Common","expanded":true,"children":[{"name":"Position","expanded":false,"children":[]},{"name":"Size","expanded":false,"children":[]}]},{"name":"Instance variables","expanded":true,"children":[]},{"name":"Behaviors","expanded":true,"children":[]},{"name":"Effects","expanded":true,"children":[]},{"name":"Container","expanded":true,"children":[]},{"name":"Properties","expanded":true,"children":[]}],"scrollPosition":0}},{"uids":[546],"properties":{"properties":[{"name":"Object type properties","expanded":true,"children":[]},{"name":"Common","expanded":true,"children":[{"name":"Position","expanded":false,"children":[]},{"name":"Size","expanded":false,"children":[]}]},{"name":"Instance variables","expanded":true,"children":[]},{"name":"Behaviors","expanded":true,"children":[{"name":"Solid [Solid]","expanded":true,"children":[]}]},{"name":"Effects","expanded":true,"children":[]},{"name":"Container","expanded":true,"children":[]},{"name":"Properties","expanded":true,"children":[]}],"scrollPosition":0}},{"uids":[545],"properties":{"properties":[{"name":"Object type properties","expanded":true,"children":[]},{"name":"Common","expanded":true,"children":[{"name":"Position","expanded":false,"children":[]},{"name":"Size","expanded":false,"children":[]}]},{"name":"Instance variables","expanded":true,"children":[]},{"name":"Behaviors","expanded":true,"children":[]},{"name":"Effects","expanded":true,"children":[]},{"name":"Container","expanded":true,"children":[]},{"name":"Properties","expanded":true,"children":[]}],"scrollPosition":0}},{"uids":[545],"properties":{"properties":[{"name":"Object type properties","expanded":true,"children":[]},{"name":"Common","expanded":true,"children":[{"name":"Position","expanded":false,"children":[]},{"name":"Size","expanded":false,"children":[]}]},{"name":"Instance variables","expanded":true,"children":[]},{"name":"Behaviors","expanded":true,"children":[]},{"name":"Effects","expanded":true,"children":[]},{"name":"Container","expanded":true,"children":[]},{"name":"Properties","expanded":true,"children":[]}],"scrollPosition":0}},{"uids":[543],"properties":{"properties":[{"name":"Object type properties","expanded":true,"children":[]},{"name":"Common","expanded":true,"children":[{"name":"Position","expanded":false,"children":[]},{"name":"Size","expanded":true,"children":[]}]},{"name":"Instance variables","expanded":true,"children":[]},{"name":"Behaviors","expanded":true,"children":[]},{"name":"Effects","expanded":true,"children":[]},{"name":"Container","expanded":true,"children":[]},{"name":"Properties","expanded":true,"children":[]}],"scrollPosition":0}},{"uids":[435],"properties":{"properties":[{"name":"Object type properties","expanded":true,"children":[]},{"name":"Common","expanded":true,"children":[{"name":"Position","expanded":false,"children":[]},{"name":"Size","expanded":false,"children":[]}]},{"name":"Instance variables","expanded":true,"children":[]},{"name":"Behaviors","expanded":true,"children":[]},{"name":"Effects","expanded":true,"children":[{"name":"Water","expanded":true,"children":[]}]},{"name":"Container","expanded":true,"children":[]},{"name":"Properties","expanded":true,"children":[]}],"scrollPosition":0}},{"uids":[421],"properties":{"properties":[{"name":"Object type properties","expanded":true,"children":[]},{"name":"Common","expanded":true,"children":[{"name":"Position","expanded":false,"children":[]},{"name":"Size","expanded":false,"children":[]}]},{"name":"Instance variables","expanded":true,"children":[]},{"name":"Behaviors","expanded":true,"children":[]},{"name":"Effects","expanded":true,"children":[]},{"name":"Container","expanded":true,"children":[]},{"name":"Properties","expanded":true,"children":[]}],"scrollPosition":0}},{"uids":[462],"properties":{"properties":[{"name":"Object type properties","expanded":true,"children":[]},{"name":"Common","expanded":true,"children":[{"name":"Position","expanded":false,"children":[]},{"name":"Size","expanded":false,"children":[]}]},{"name":"Instance variables","expanded":true,"children":[]},{"name":"Behaviors","expanded":true,"children":[]},{"name":"Effects","expanded":true,"children":[]},{"name":"Container","expanded":true,"children":[]},{"name":"Properties","expanded":true,"children":[]}],"scrollPosition":0}},{"uids":[409],"properties":{"properties":[{"name":"Object type properties","expanded":true,"children":[]},{"name":"Common","expanded":true,"children":[{"name":"Position","expanded":false,"children":[]},{"name":"Size","expanded":false,"children":[]}]},{"name":"Instance variables","expanded":true,"children":[]},{"name":"Behaviors","expanded":true,"children":[]},{"name":"Effects","expanded":true,"children":[]},{"name":"Container","expanded":true,"children":[]},{"name":"Properties","expanded":true,"children":[]}],"scrollPosition":0}},{"uids":[680],"properties":{"properties":[{"name":"Object type properties","expanded":true,"children":[]},{"name":"Common","expanded":true,"children":[{"name":"Position","expanded":false,"children":[]},{"name":"Size","expanded":false,"children":[]}]},{"name":"Instance variables","expanded":true,"children":[]},{"name":"Behaviors","expanded":true,"children":[]},{"name":"Effects","expanded":true,"children":[]},{"name":"Container","expanded":true,"children":[]},{"name":"Properties","expanded":true,"children":[]}],"scrollPosition":0}},{"uids":[688],"properties":{"properties":[{"name":"Object type properties","expanded":true,"children":[]},{"name":"Common","expanded":true,"children":[{"name":"Position","expanded":false,"children":[]},{"name":"Size","expanded":false,"children":[]}]},{"name":"Instance variables","expanded":true,"children":[]},{"name":"Behaviors","expanded":true,"children":[]},{"name":"Effects","expanded":true,"children":[{"name":"PolkaDot","expanded":true,"children":[]},{"name":"WarpRipple","expanded":true,"children":[]},{"name":"HexagonalPixellate","expanded":true,"children":[]},{"name":"ScanLines","expanded":true,"children":[]}]},{"name":"Container","expanded":true,"children":[]},{"name":"Properties","expanded":true,"children":[]}],"scrollPosition":0}},{"uids":[22],"properties":{"properties":[{"name":"Object type properties","expanded":true,"children":[]},{"name":"Common","expanded":true,"children":[{"name":"Position","expanded":false,"children":[]},{"name":"Size","expanded":false,"children":[]}]},{"name":"Instance variables","expanded":true,"children":[]},{"name":"Behaviors","expanded":true,"children":[]},{"name":"Effects","expanded":true,"children":[]},{"name":"Container","expanded":true,"children":[]},{"name":"Properties","expanded":true,"children":[]}],"scrollPosition":0}},{"uids":[544],"properties":{"properties":[{"name":"Object type properties","expanded":true,"children":[]},{"name":"Common","expanded":true,"children":[{"name":"Position","expanded":false,"children":[]},{"name":"Size","expanded":false,"children":[]}]},{"name":"Instance variables","expanded":true,"children":[]},{"name":"Behaviors","expanded":true,"children":[]},{"name":"Effects","expanded":true,"children":[]},{"name":"Container","expanded":true,"children":[]},{"name":"Properties","expanded":true,"children":[]}],"scrollPosition":0}},{"uids":[564],"properties":{"properties":[{"name":"Common","expanded":true,"children":[{"name":"Position","expanded":false,"children":[]},{"name":"Size","expanded":false,"children":[]}]},{"name":"Effects","expanded":true,"children":[]}],"scrollPosition":0}},{"uids":[693],"properties":{"properties":[{"name":"Object type properties","expanded":true,"children":[]},{"name":"Common","expanded":true,"children":[{"name":"Position","expanded":false,"children":[]},{"name":"Size","expanded":false,"children":[]}]},{"name":"Instance variables","expanded":true,"children":[]},{"name":"Behaviors","expanded":true,"children":[]},{"name":"Effects","expanded":true,"children":[]},{"name":"Container","expanded":true,"children":[]},{"name":"Properties","expanded":true,"children":[]}],"scrollPosition":0}},{"uids":[544],"properties":{"properties":[{"name":"Object type properties","expanded":true,"children":[]},{"name":"Common","expanded":true,"children":[{"name":"Position","expanded":false,"children":[]},{"name":"Size","expanded":false,"children":[]}]},{"name":"Instance variables","expanded":true,"children":[]},{"name":"Behaviors","expanded":true,"children":[]},{"name":"Effects","expanded":true,"children":[]},{"name":"Container","expanded":true,"children":[]},{"name":"Properties","expanded":true,"children":[]}],"scrollPosition":0}},{"uids":[694],"properties":{"properties":[{"name":"Object type properties","expanded":true,"children":[]},{"name":"Common","expanded":true,"children":[{"name":"Position","expanded":false,"children":[]},{"name":"Size","expanded":false,"children":[]}]},{"name":"Instance variables","expanded":true,"children":[]},{"name":"Behaviors","expanded":true,"children":[]},{"name":"Effects","expanded":true,"children":[]},{"name":"Container","expanded":true,"children":[]},{"name":"Properties","expanded":true,"children":[]}],"scrollPosition":0}},{"uids":[530],"properties":{"properties":[{"name":"Object type properties","expanded":true,"children":[]},{"name":"Common","expanded":true,"children":[{"name":"Position","expanded":false,"children":[]},{"name":"Size","expanded":false,"children":[]}]},{"name":"Instance variables","expanded":true,"children":[]},{"name":"Behaviors","expanded":true,"children":[]},{"name":"Effects","expanded":true,"children":[]},{"name":"Container","expanded":true,"children":[]},{"name":"Properties","expanded":true,"children":[]},{"name":"Initial particle properties","expanded":true,"children":[]},{"name":"Particle lifetime properties","expanded":true,"children":[]}],"scrollPosition":0}},{"uids":[695],"properties":{"properties":[{"name":"Object type properties","expanded":true,"children":[]},{"name":"Common","expanded":true,"children":[{"name":"Position","expanded":false,"children":[]},{"name":"Size","expanded":false,"children":[]}]},{"name":"Instance variables","expanded":true,"children":[]},{"name":"Behaviors","expanded":true,"children":[]},{"name":"Effects","expanded":true,"children":[]},{"name":"Container","expanded":true,"children":[]},{"name":"Properties","expanded":true,"children":[]}],"scrollPosition":0}},{"uids":[615],"properties":{"properties":[{"name":"Object type properties","expanded":true,"children":[]},{"name":"Common","expanded":true,"children":[{"name":"Position","expanded":false,"children":[]},{"name":"Size","expanded":false,"children":[]}]},{"name":"Instance variables","expanded":true,"children":[]},{"name":"Behaviors","expanded":true,"children":[]},{"name":"Effects","expanded":true,"children":[]},{"name":"Container","expanded":true,"children":[]},{"name":"Properties","expanded":true,"children":[]}],"scrollPosition":0}},{"uids":[690],"properties":{"properties":[{"name":"Object type properties","expanded":true,"children":[]},{"name":"Common","expanded":true,"children":[{"name":"Position","expanded":false,"children":[]},{"name":"Size","expanded":true,"children":[]}]},{"name":"Instance variables","expanded":true,"children":[]},{"name":"Behaviors","expanded":true,"children":[{"name":"Sine","expanded":true,"children":[]},{"name":"Sine2","expanded":true,"children":[]}]},{"name":"Effects","expanded":true,"children":[]},{"name":"Container","expanded":true,"children":[]},{"name":"Properties","expanded":true,"children":[]}],"scrollPosition":0}},{"uids":[690],"properties":{"properties":[{"name":"Object type properties","expanded":true,"children":[]},{"name":"Common","expanded":true,"children":[{"name":"Position","expanded":false,"children":[]},{"name":"Size","expanded":true,"children":[]}]},{"name":"Instance variables","expanded":true,"children":[]},{"name":"Behaviors","expanded":true,"children":[{"name":"Sine","expanded":true,"children":[]},{"name":"Sine2","expanded":true,"children":[]}]},{"name":"Effects","expanded":true,"children":[]},{"name":"Container","expanded":true,"children":[]},{"name":"Properties","expanded":true,"children":[]}],"scrollPosition":0}},{"uids":[623],"properties":{"properties":[{"name":"Object type properties","expanded":true,"children":[]},{"name":"Common","expanded":true,"children":[{"name":"Position","expanded":false,"children":[]},{"name":"Size","expanded":false,"children":[]}]},{"name":"Instance variables","expanded":true,"children":[]},{"name":"Behaviors","expanded":true,"children":[]},{"name":"Effects","expanded":true,"children":[]},{"name":"Container","expanded":true,"children":[]},{"name":"Properties","expanded":true,"children":[]}],"scrollPosition":0}}]}